nornir_srl/__init__.py
nornir_srl/cli.py
nornir_srl/connections/__init__.py
nornir_srl/connections/helpers.py
nornir_srl/connections/interfaces.py
nornir_srl/connections/layer2.py
nornir_srl/connections/neighbor_discovery.py
nornir_srl/connections/routing.py
nornir_srl/connections/srlinux.py
nornir_srl/connections/system.py
nornir_srl/tasks/__init__.py
nornir_srl/tasks/helpers.py
nornir_srl/tasks/srl_config.py
nornir_srl/utils/__init__.py
nornir_srl/utils/logging_config.py
nornir_srl-0.3.2.dist-info/licenses/LICENSE
nornir_srl-0.3.2.dist-info/METADATA
nornir_srl-0.3.2.dist-info/WHEEL
nornir_srl-0.3.2.dist-info/entry_points.txt
nornir_srl-0.3.2.dist-info/top_level.txt
nornir_srl-0.3.2.dist-info/RECORD
