Metadata-Version: 2.4
Name: nornir-srl
Version: 0.3.2
Summary: Nornir connection plugin for SRLinux
Author: Florian Schwarz
Author-email: Walter De Smedt <walter.de.smedt@gmail.com>
Requires-Python: >=3.9
License-File: LICENSE
Requires-Dist: nornir>=3.5.0
Requires-Dist: nornir-utils>=0.2.0
Requires-Dist: pygnmi>=0.8.15
Requires-Dist: nornir-jinja2>=0.2.0
Requires-Dist: nornir-scrapli>=2025.1.30
Requires-Dist: rich>=12.6.0
Requires-Dist: natsort>=8.4.0
Requires-Dist: jsondiff>=2.2.1
Requires-Dist: click>=8.1.3
Requires-Dist: jmespath>=1.0.1
Requires-Dist: setuptools>=75.4.0
Requires-Dist: pyyaml>=6.0.2
Requires-Dist: typer>=0.16.0
Provides-Extra: dev
Requires-Dist: pytest>=5.2; extra == "dev"
Requires-Dist: blessings>=1.7; extra == "dev"
Requires-Dist: black>=25.1.0; extra == "dev"
Requires-Dist: mypy>=1.16.0; extra == "dev"
Requires-Dist: types-setuptools>=80.9.0; extra == "dev"
Dynamic: license-file
